moex/__init__.py
moex/api.py
moex/data_classes.py
moex/design.py
moex/exceptions.py
moex/handlers.py
moex/meta.py
moex/templates.py
moex/utils.py
moex-1.0.0.dist-info/LICENSE
moex-1.0.0.dist-info/METADATA
moex-1.0.0.dist-info/WHEEL
moex-1.0.0.dist-info/RECORD
