Metadata-Version: 2.1
Name: moex
Version: 1.0.0
Summary: MoscowExchange ISS Queries implementation
License: MIT
Keywords: moex,moex iss,async moex,moscow,exchange,MoscowExchange,finance,stocks
Author: Michael R. Kisel
Author-email: aioboy@yandex.com
Maintainer: Michael R. Kisel
Maintainer-email: aioboy@yandex.com
Requires-Python: >=3.8.1,<3.13
Classifier: Development Status :: 5 - Production/Stable
Classifier: Framework :: AsyncIO
Classifier: Intended Audience :: Developers
Classifier: Intended Audience :: Education
Classifier: Intended Audience :: End Users/Desktop
Classifier: Intended Audience :: Financial and Insurance Industry
Classifier: Intended Audience :: Science/Research
Classifier: License :: OSI Approved :: MIT License
Classifier: Operating System :: OS Independent
Classifier: Programming Language :: Python
Classifier: Programming Language :: Python :: 3
Classifier: Programming Language :: Python :: 3.9
Classifier: Programming Language :: Python :: 3.10
Classifier: Programming Language :: Python :: 3.11
Classifier: Programming Language :: Python :: 3.12
Classifier: Programming Language :: Python :: 3.8
Classifier: Topic :: Home Automation
Classifier: Topic :: Internet
Classifier: Topic :: Office/Business
Classifier: Topic :: Office/Business :: Financial
Classifier: Topic :: Office/Business :: Financial :: Point-Of-Sale
Classifier: Topic :: Office/Business :: News/Diary
Classifier: Topic :: Scientific/Engineering
Classifier: Topic :: Scientific/Engineering :: Artificial Intelligence
Requires-Dist: aiohttp (<=3.10.11)
Requires-Dist: beautifulsoup4 (<=4.11.1)
Requires-Dist: lxml (<=4.9.1)
Requires-Dist: numpy (<2.0.0)
Requires-Dist: pandas (<=2.0.3)
Requires-Dist: rich (<=12.6.0)
Project-URL: documentation, https://aioboy.tech/p/moex/
Project-URL: homepage, https://pypi.org/project/moex
Project-URL: repository, https://gitlab.com/aioboy/moex/
